{
  "version": "7",
  "dialect": "postgresql",
  "entries": [
    {
      "idx": 0,
      "version": "7",
      "when": 1783357951284,
      "tag": "0000_soft_shooting_star",
      "breakpoints": true
    },
    {
      "idx": 1,
      "version": "7",
      "when": 1783361230984,
      "tag": "0001_small_mandroid",
      "breakpoints": true
    },
    {
      "idx": 2,
      "version": "7",
      "when": 1783371312178,
      "tag": "0002_luxuriant_mandroid",
      "breakpoints": true
    },
    {
      "idx": 3,
      "version": "7",
      "when": 1783374297364,
      "tag": "0003_ambitious_tyger_tiger",
      "breakpoints": true
    },
    {
      "idx": 4,
      "version": "7",
      "when": 1783384575648,
      "tag": "0004_dark_fabian_cortez",
      "breakpoints": true
    },
    {
      "idx": 5,
      "version": "7",
      "when": 1783384926529,
      "tag": "0005_swift_firestar",
      "breakpoints": true
    },
    {
      "idx": 6,
      "version": "7",
      "when": 1783385603810,
      "tag": "0006_tearful_molecule_man",
      "breakpoints": true
    },
    {
      "idx": 7,
      "version": "7",
      "when": 1783390249244,
      "tag": "0007_mute_masked_marvel",
      "breakpoints": true
    },
    {
      "idx": 8,
      "version": "7",
      "when": 1783440582903,
      "tag": "0008_lonely_fallen_one",
      "breakpoints": true
    },
    {
      "idx": 9,
      "version": "7",
      "when": 1783444789049,
      "tag": "0009_curved_rhodey",
      "breakpoints": true
    },
    {
      "idx": 10,
      "version": "7",
      "when": 1783462938968,
      "tag": "0010_sudden_amphibian",
      "breakpoints": true
    },
    {
      "idx": 11,
      "version": "7",
      "when": 1783519536014,
      "tag": "0011_useful_vivisector",
      "breakpoints": true
    },
    {
      "idx": 12,
      "version": "7",
      "when": 1783519758911,
      "tag": "0012_high_spacker_dave",
      "breakpoints": true
    }
  ]
}